labthings_fastapi/__init__.py
labthings_fastapi/actions.py
labthings_fastapi/base_descriptor.py
labthings_fastapi/deps.py
labthings_fastapi/endpoints.py
labthings_fastapi/exceptions.py
labthings_fastapi/invocation_contexts.py
labthings_fastapi/invocations.py
labthings_fastapi/logs.py
labthings_fastapi/notifications.py
labthings_fastapi/properties.py
labthings_fastapi/py.typed
labthings_fastapi/testing.py
labthings_fastapi/thing.py
labthings_fastapi/thing_server_interface.py
labthings_fastapi/thing_slots.py
labthings_fastapi/websockets.py
labthings_fastapi/client/__init__.py
labthings_fastapi/client/in_server.py
labthings_fastapi/client/outputs.py
labthings_fastapi/dependencies/__init__.py
labthings_fastapi/dependencies/blocking_portal.py
labthings_fastapi/dependencies/invocation.py
labthings_fastapi/dependencies/metadata.py
labthings_fastapi/dependencies/raw_thing.py
labthings_fastapi/dependencies/thing.py
labthings_fastapi/dependencies/thing_server.py
labthings_fastapi/example_things/__init__.py
labthings_fastapi/outputs/__init__.py
labthings_fastapi/outputs/blob.py
labthings_fastapi/outputs/mjpeg_stream.py
labthings_fastapi/server/__init__.py
labthings_fastapi/server/cli.py
labthings_fastapi/server/config_model.py
labthings_fastapi/server/fallback.html.jinja
labthings_fastapi/server/fallback.py
labthings_fastapi/thing_description/__init__.py
labthings_fastapi/thing_description/_model.py
labthings_fastapi/thing_description/td-json-schema-validation.json
labthings_fastapi/thing_description/validation.py
labthings_fastapi/types/__init__.py
labthings_fastapi/types/numpy.py
labthings_fastapi/utilities/__init__.py
labthings_fastapi/utilities/introspection.py
labthings_fastapi-0.0.14.dist-info/METADATA
labthings_fastapi-0.0.14.dist-info/WHEEL
labthings_fastapi-0.0.14.dist-info/entry_points.txt
labthings_fastapi-0.0.14.dist-info/licenses/LICENSE
labthings_fastapi-0.0.14.dist-info/RECORD
