Metadata-Version: 2.4
Name: labthings-fastapi
Version: 0.0.14
Summary: An implementation of LabThings using FastAPI
Project-URL: Homepage, https://github.com/labthings/labthings-fastapi
Project-URL: Bug Tracker, https://github.com/labthings/labthings-fastapi/issues
Author-email: Richard Bowman <richard.bowman@cantab.net>
License-File: LICENSE
Classifier: License :: OSI Approved :: MIT License
Classifier: Operating System :: OS Independent
Classifier: Programming Language :: Python :: 3
Requires-Python: >=3.10
Requires-Dist: anyio~=4.0
Requires-Dist: fastapi[all]>=0.115.0
Requires-Dist: httpx
Requires-Dist: jsonschema
Requires-Dist: numpy>=1.20
Requires-Dist: pydantic~=2.10.6
Requires-Dist: typing-extensions
Requires-Dist: zeroconf>=0.28.0
Provides-Extra: dev
Requires-Dist: codespell; extra == 'dev'
Requires-Dist: flake8; extra == 'dev'
Requires-Dist: flake8-pyproject; extra == 'dev'
Requires-Dist: flake8-rst; extra == 'dev'
Requires-Dist: flake8-rst-docstrings; extra == 'dev'
Requires-Dist: mypy<2,>=1.6.1; extra == 'dev'
Requires-Dist: pillow; extra == 'dev'
Requires-Dist: pydoclint[flake8]; extra == 'dev'
Requires-Dist: pytest-cov; extra == 'dev'
Requires-Dist: pytest-mock; extra == 'dev'
Requires-Dist: pytest>=8.4.0; extra == 'dev'
Requires-Dist: ruff>=0.1.3; extra == 'dev'
Requires-Dist: sphinx-autoapi; extra == 'dev'
Requires-Dist: sphinx-rtd-theme; extra == 'dev'
Requires-Dist: sphinx-toolbox; extra == 'dev'
Requires-Dist: sphinx>=7.2; extra == 'dev'
Requires-Dist: types-jsonschema; extra == 'dev'
